MANIFEST.in
README.md
requirements.txt
setup.cfg
setup.py
start-server.sh
slotty/__init__.py
slotty/app.py
slotty/config.py
slotty.egg-info/PKG-INFO
slotty.egg-info/SOURCES.txt
slotty.egg-info/dependency_links.txt
slotty.egg-info/not-zip-safe
slotty.egg-info/requires.txt
slotty.egg-info/top_level.txt
slotty/static/__ini__.py
slotty/static/css/bootstrap-theme.min.css
slotty/static/css/bootstrap.min.css
slotty/static/css/style.css
slotty/static/img/glyphicons-halflings-white.png
slotty/static/img/glyphicons-halflings.png
slotty/static/js/bootstrap-3.0.3.min.js
slotty/static/js/jquery-2.0.3.min.js
slotty/static/js/jquery.color-2.1.2.min.js
slotty/static/js/socket.io-0.9.16.min.js
slotty/templates/index.html